MANIFEST.in
README.txt
setup.py
collective/__init__.py
collective.templateengines.egg-info/PKG-INFO
collective.templateengines.egg-info/SOURCES.txt
collective.templateengines.egg-info/dependency_links.txt
collective.templateengines.egg-info/entry_points.txt
collective.templateengines.egg-info/namespace_packages.txt
collective.templateengines.egg-info/not-zip-safe
collective.templateengines.egg-info/requires.txt
collective.templateengines.egg-info/top_level.txt
collective/templateengines/__init__.py
collective/templateengines/interfaces.py
collective/templateengines/utils.py
collective/templateengines/backends/__init__.py
collective/templateengines/backends/cheetah.py
collective/templateengines/backends/djangotemplates.py
collective/templateengines/backends/jinja.py
collective/templateengines/context/.plone.py.un~
collective/templateengines/context/__init__.py
collective/templateengines/context/jinjazope.py
collective/templateengines/context/plone.py
collective/templateengines/context/tags.py
collective/templateengines/tests/__init__.py
collective/templateengines/tests/base_test.py
collective/templateengines/tests/test_cheetah.py
collective/templateengines/tests/test_django.py
collective/templateengines/tests/test_jinja.py
docs/HISTORY.txt