Metadata-Version: 1.0
Name: collective.templateengines
Version: 0.3.5
Summary: Template engine abstraction layer for Python
Home-page: http://www.twinapex.com/for-developers/open-source/for-plone/easy-template
Author: Mikko Ohtamaa
Author-email: mikko.ohtamaa@twinapex.com
License: License :: OSI Approved :: BSD License
Keywords: template templates engine python interface zope cheetah django backend utils generic
Platform: UNKNOWN
Classifier: Programming Language :: Python
Classifier: Topic :: Software Development :: Libraries :: Python Modules
